[
  {
    "id": "classic crime fiction",
    "name": "Clássico"
  },
  {
    "id": "african american mistery",
    "name": "Black Noir"
  },
  {
    "id": "Brazilian Crime Fiction",
    "name": "Brasileiro"
  },
  {
    "id": "cold war thrillers",
    "name": "Guerra Fria"
  },
  {
    "id": "war crime fiction",
    "name": "Crimes de Guerra"
  },
  {
    "id": "conspiracao",
    "name": "Conspiração"
  },
  {
    "id": "cozy",
    "name": "Cozy Mystery"
  },
  {
    "id": "detective fiction",
    "name": "Detetive"
  },
  {
    "id": "domestic noir",
    "name": "Domestic Noir"
  },
  {
    "id": "espionagem",
    "name": "Espionagem"
  },
  {
    "id": "forense",
    "name": "Forense"
  },
  {
    "id": "giallo",
    "name": "Giallo"
  },
  {
    "id": "historical crime fiction",
    "name": "Histórico"
  },
  {
    "id": "international crime fiction",
    "name": "International Crime Fiction"
  },
  {
    "id": "inverted",
    "name": "Invertido (Howcatchem)"
  },
    {
    "id": "jovem-adulto",
    "name": "Jovem Adulto (YA)"
  },
  {
    "id": "erotic mistery",
    "name": "Mistério Erótico"
  },
  {
    "id": "noir",
    "name": "Noir (hard-boiled)"
  },
  {
    "id": "asian noir",
    "name": "Noir Asiático"
  },
  {
    "id": "nordico",
    "name": "Nórdico"
  },
  {
    "id": "honkaku",
    "name": "Ortodoxo (Honkaku)"
  },
  {
    "id": "outback noir",
    "name": "Outback Noir"
  },
  {
    "id": "political thriller",
    "name": "Político"
  },
    {
    "id": "procedural",
    "name": "Procedural"
  },
  {
    "id": "psicologico",
    "name": "Psicológico"
  },
    {
    "id": "locked-room",
    "name": "Quarto Fechado (Locked-Room)"
  },
  {
    "id": "queer mystery",
    "name": "Queer Mystery"
  },
  {
    "id": "regionalkrimi",
    "name": "Regionalkrimi (Alemanha)"
  },
    {
    "id": "sobrenatural",
    "name": "Sobrenatural"
  },
    {
    "id": "soviet noir",
    "name": "Soviet Noir"
  },
  {
    "id": "latin-american crime fiction",
    "name": "Sul-Americano"
  },
  {
    "id": "tartan noir",
    "name": "Tartan Noir"
  },
  {
    "id": "techno",
    "name": "Techno"
  },
  {
    "id": "thriller français",
    "name": "Thriller Francês"
  },
  {
    "id": "legal",
    "name": "Thriller Jurídico"
  },
  {
    "id": "whodunit",
    "name": "Whodunit"
  }
]